memory/zero_extend.sv
module zero_extend #(
    parameter LEN = 32,
    parameter HALF_LEN = 16,
    parameter BYTE_LEN = 8
) (
    input logic [HALF_LEN-1:0] half_input,
    input logic [BYTE_LEN-1:0] byte_input,
    output logic [LEN-1:0] he,
    output logic [LEN-1:0] be
);

assign be = {{24{1'b0}}, byte_input};
assign he = {{16{1'b0}}, half_input};
    
endmodule

memory/half_byte_word.sv
module half_byte_word #(
    parameter CPU_WORD = 32,
    parameter HALF_LEN = 16,
    parameter BYTE_LEN = 8
) (
    input logic lw, // load word
    input logic lb, // load byte
    input logic lh, // load half
    input [CPU_WORD-1:0] data,
    output [CPU_WORD-1:0] dout
);
    logic [CPU_WORD-1:0] he;
    logic [CPU_WORD-1:0] be;
    logic [HALF_LEN-1:0] h;
    logic [BYTE_LEN-1:0] b;

    assign h = data[HALF_LEN-1:0];
    assign b = data[BYTE_LEN-1:0];

    zero_extend ze(h,b,he,be);

    if(lh)  assign dout = he;
    else if(lb) assign dout = be;
    else assign dout = data;

endmodule

memory/ram.sv
module ram #(
    parameter ADDRESS_LENGTH = 32,
    parameter WORD_LENGTH = 8
) (
    //input logic we,
    input logic [ADDRESS_LENGTH-1:0] wd,
    input logic sw,
    input logic sh,
    input logic sb,
    input logic [ADDRESS_LENGTH-1:0] a,
    input logic clk,
    output logic [ADDRESS_LENGTH-1:0] rd
);

logic [WORD_LENGTH-1:0] ram_array[32'h1FFFF:0];

logic [WORD_LENGTH-1:0] d0;
logic [WORD_LENGTH-1:0] d1;
logic [WORD_LENGTH-1:0] d2;
logic [WORD_LENGTH-1:0] d3;

assign d0 = wd[WORD_LENGTH-1:0];
assign d1 = wd[2*(WORD_LENGTH)-1:WORD_LENGTH];
assign d2 = wd[3*(WORD_LENGTH)-1:2*(WORD_LENGTH)];
assign d3 = wd[4*(WORD_LENGTH)-1:3*(WORD_LENGTH)];

initial begin
    $display("Loading data memory.");
    $readmemh("dataram.mem", ram_array);
end

assign rd = {ram_array[a+3],ram_array[a+2],ram_array[a+1],ram_array[a]};
    
always_ff @(posedge clk) begin
    if (sb) begin
        ram_array[a] <= d0;
    end
    else if (sh) begin
        ram_array[a] <= d0;
        ram_array[a+1] <= d1;
    end
    else if (sw) begin
        ram_array[a] <= d0;
        ram_array[a+1] <= d1;
        ram_array[a+2] <= d2;
        ram_array[a+3] <= d3;
    end
end

endmodule

memory/top_memory.sv
/* verilator lint_off MODDUP */
module top_memory #(
    parameter WIDTH = 32
) (
    input logic clk,
    // input logic memWrite_M,
    input logic sw,
    input logic sh,
    input logic sb,
    input logic lw,
    input logic lh,
    input logic lb,
    input logic [WIDTH-1:0] ALUResult_M,
    input logic [WIDTH-1:0] writeData_M,
    output logic [WIDTH-1:0] readData_M
);

logic [WIDTH-1:0] dout;

ram ram(
    .sw(sw),
    .sh(sh),
    .sb(sb),
    .wd(writeData_M),
    .a(ALUResult_M),
    .clk(clk),
    .rd(dout)
);

half_byte_word hbw(
    .lw(lw),
    .lh(lh),
    .lb(lb),
    .data(dout),
    .dout(readData_M)
);

endmodule

memory/top.vcd
$version Generated by VerilatedVcd $end
$date Fri Dec  9 14:26:47 2022 $end
$timescale 1ps $end

 $scope module TOP $end
  $var wire 32 / ALUResult_M [31:0] $end
  $var wire  1 ( clk $end
  $var wire  1 . lb $end
  $var wire  1 - lh $end
  $var wire  1 , lw $end
  $var wire 32 1 readData_M [31:0] $end
  $var wire  1 + sb $end
  $var wire  1 * sh $end
  $var wire  1 ) sw $end
  $var wire 32 0 writeData_M [31:0] $end
  $scope module top_memory $end
   $var wire 32 / ALUResult_M [31:0] $end
   $var wire 32 6 WIDTH [31:0] $end
   $var wire  1 ( clk $end
   $var wire 32 # dout [31:0] $end
   $var wire  1 . lb $end
   $var wire  1 - lh $end
   $var wire  1 , lw $end
   $var wire 32 1 readData_M [31:0] $end
   $var wire  1 + sb $end
   $var wire  1 * sh $end
   $var wire  1 ) sw $end
   $var wire 32 0 writeData_M [31:0] $end
   $scope module hbw $end
    $var wire 32 8 BYTE_LEN [31:0] $end
    $var wire 32 6 CPU_WORD [31:0] $end
    $var wire 32 7 HALF_LEN [31:0] $end
    $var wire  8 ' b [7:0] $end
    $var wire 32 % be [31:0] $end
    $var wire 32 # data [31:0] $end
    $var wire 32 1 dout [31:0] $end
    $var wire 16 & h [15:0] $end
    $var wire 32 $ he [31:0] $end
    $var wire  1 . lb $end
    $var wire  1 - lh $end
    $var wire  1 , lw $end
    $scope module ze $end
     $var wire 32 8 BYTE_LEN [31:0] $end
     $var wire 32 7 HALF_LEN [31:0] $end
     $var wire 32 6 LEN [31:0] $end
     $var wire 32 % be [31:0] $end
     $var wire  8 ' byte_input [7:0] $end
     $var wire 16 & half_input [15:0] $end
     $var wire 32 $ he [31:0] $end
    $upscope $end
   $upscope $end
   $scope module ram $end
    $var wire 32 6 ADDRESS_LENGTH [31:0] $end
    $var wire 32 8 WORD_LENGTH [31:0] $end
    $var wire 32 / a [31:0] $end
    $var wire  1 ( clk $end
    $var wire  8 2 d0 [7:0] $end
    $var wire  8 3 d1 [7:0] $end
    $var wire  8 4 d2 [7:0] $end
    $var wire  8 5 d3 [7:0] $end
    $var wire 32 # rd [31:0] $end
    $var wire  1 + sb $end
    $var wire  1 * sh $end
    $var wire  1 ) sw $end
    $var wire 32 0 wd [31:0] $end
   $upscope $end
  $upscope $end
 $upscope $end
$enddefinitions $end


#0
b00000000000000000000000000000000 #
b00000000000000000000000000000000 $
b00000000000000000000000000000000 %
b0000000000000000 &
b00000000 '
1(
0)
0*
0+
0,
0-
0.
b00000000000000000000000000000000 /
b00000000000000000000000000000000 0
b00000000000000000000000000000000 1
b00000000 2
b00000000 3
b00000000 4
b00000000 5
b00000000000000000000000000100000 6
b00000000000000000000000000010000 7
b00000000000000000000000000001000 8
#1
0(
#2
1(
1)
b00000000000000000001000000000001 /
b11111111111111111111111111111111 0
b11111111 2
b11111111 3
b11111111 4
b11111111 5
#3
0(
#4
b11111111111111111111111111111111 #
b00000000000000001111111111111111 $
b00000000000000000000000011111111 %
b1111111111111111 &
b11111111 '
1(
#5
0(
#6
1(
#7
0(
#8
1(
0)
1*
1,
b10101010101010101010101010101010 0
b10101010 2
b10101010 3
b10101010 4
b10101010 5
#9
0(
b11111111111111111111111111111111 1
#10
b11111111111111111010101010101010 #
b00000000000000001010101010101010 $
b00000000000000000000000010101010 %
b1010101010101010 &
b10101010 '
1(
b11111111111111111010101010101010 1
#11
0(
#12
1(
0*
1+
b10111011101110111011101110111011 0
b10111011 2
b10111011 3
b10111011 4
b10111011 5
#13
0(
#14
b11111111111111111010101010111011 #
b00000000000000001010101010111011 $
b00000000000000000000000010111011 %
b1010101010111011 &
b10111011 '
1(
b11111111111111111010101010111011 1
#15
0(
#16
1(
0+
