memory/sign_extend.sv
/* verilator lint_off LATCH */
module sign_extend #(
    parameter WORD_LENGTH = 32,
    parameter BYTE_LEN = 8
) (
    input logic [BYTE_LEN-1:0] din,
    input logic s,
    output logic [WORD_LENGTH-1:0] dout
);

logic sign;
always_comb begin
    if(s) begin
        assign sign = din[7];
        case (sign)
            1: assign dout = {{24{1'b1}},din};
            0: assign dout = {{24{1'b0}},din};
            default: assign dout = {{24{1'b0}},din};
        endcase
    end
    else begin
        assign dout = {{24{1'b0}},din};
    end    
end
endmodule

memory/half_extend.sv
module half_extend #(
    parameter WORD_LENGTH = 32,
    parameter HALF_LEN = 16
) (
    input logic [HALF_LEN-1:0] din,
    input logic s,
    output logic [WORD_LENGTH-1:0] dout
);

logic sign;
always_comb begin
    if(s) begin
        sign = din[WORD_LENGTH-1];
        case (sign)
            1: dout = {{16{1'b1}},din};
            0: dout = {{16{1'b0}},din};
            default: dout = {{16{1'b0}},din};
        endcase
    end
    else begin
        dout = {{16{1'b0}},din};
    end    
end
endmodule

memory/half_byte_word.sv
module half_byte_word #(
    parameter CPU_WORD = 32,
    parameter HALF_LEN = 16,
    parameter BYTE_LEN = 8
) (
    input logic lw, // load word
    input logic lb, // load byte
    input logic lh, // load half
    input logic s,
    input [CPU_WORD-1:0] data,
    output [CPU_WORD-1:0] dout
);
    logic [CPU_WORD-1:0] he;
    logic [CPU_WORD-1:0] be;
    logic [HALF_LEN-1:0] h;
    logic [BYTE_LEN-1:0] b;

    assign h = data[HALF_LEN-1:0];
    assign b = data[BYTE_LEN-1:0];

    half_extend h_e(h,he);
    sign_extend s_e(b,s,be);

    always_comb begin
        if(lh)  begin
            assign dout = he;
        end
        else if(lb) begin
            assign dout = be;
        end
        else if(lw) begin
            assign dout = data;
        end
        else begin
            assign dout = {CPU_WORD{1'b0}};
        end
    end

endmodule

memory/ram.sv
module ram #(
    parameter ADDRESS_LENGTH = 32,
    parameter WORD_LENGTH = 8
) (
    //input logic we,
    input logic [ADDRESS_LENGTH-1:0] wd,
    input logic sw,
    input logic sh,
    input logic sb,
    input logic [ADDRESS_LENGTH-1:0] a,
    input logic clk,
    output logic [ADDRESS_LENGTH-1:0] rd
);

logic [WORD_LENGTH-1:0] ram_array[32'h1FFFF:0];

logic [WORD_LENGTH-1:0] d0;
logic [WORD_LENGTH-1:0] d1;
logic [WORD_LENGTH-1:0] d2;
logic [WORD_LENGTH-1:0] d3;

assign d0 = wd[WORD_LENGTH-1:0];
assign d1 = wd[2*(WORD_LENGTH)-1:WORD_LENGTH];
assign d2 = wd[3*(WORD_LENGTH)-1:2*(WORD_LENGTH)];
assign d3 = wd[4*(WORD_LENGTH)-1:3*(WORD_LENGTH)];

initial begin
    $display("Loading data memory.");
    $readmemh("dataram.mem", ram_array);
end

assign rd = {ram_array[a+3],ram_array[a+2],ram_array[a+1],ram_array[a]};
    
always_ff @(posedge clk) begin
    if (sb) begin
        ram_array[a] <= d0;
    end
    else if (sh) begin
        ram_array[a] <= d0;
        ram_array[a+1] <= d1;
    end
    else if (sw) begin
        ram_array[a] <= d0;
        ram_array[a+1] <= d1;
        ram_array[a+2] <= d2;
        ram_array[a+3] <= d3;
    end
end

endmodule

memory/top_memory.sv
/* verilator lint_off MODDUP */
module top_memory #(
    parameter WIDTH = 32
) (
    input logic clk,
    // input logic memWrite_M,
    input logic sw,
    input logic sh,
    input logic sb,
    input logic lw,
    input logic lh,
    input logic lb,
    input logic s,
    input logic [WIDTH-1:0] ALUResult_M,
    input logic [WIDTH-1:0] writeData_M,
    output logic [WIDTH-1:0] readData_M
);

logic [WIDTH-1:0] dout;

ram ram(
    .sw(sw),
    .sh(sh),
    .sb(sb),
    .wd(writeData_M),
    .a(ALUResult_M),
    .clk(clk),
    .rd(dout)
);

half_byte_word hbw(
    .lw(lw),
    .lh(lh),
    .lb(lb),
    .s(s),
    .data(dout),
    .dout(readData_M)
);

endmodule

memory/top.vcd
$version Generated by VerilatedVcd $end
$date Tue Dec 13 16:48:48 2022 $end
$timescale 1ps $end

 $scope module TOP $end
  $var wire 32 2 ALUResult_M [31:0] $end
  $var wire  1 * clk $end
  $var wire  1 0 lb $end
  $var wire  1 / lh $end
  $var wire  1 . lw $end
  $var wire 32 4 readData_M [31:0] $end
  $var wire  1 1 s $end
  $var wire  1 - sb $end
  $var wire  1 , sh $end
  $var wire  1 + sw $end
  $var wire 32 3 writeData_M [31:0] $end
  $scope module top_memory $end
   $var wire 32 2 ALUResult_M [31:0] $end
   $var wire 32 9 WIDTH [31:0] $end
   $var wire  1 * clk $end
   $var wire 32 # dout [31:0] $end
   $var wire  1 0 lb $end
   $var wire  1 / lh $end
   $var wire  1 . lw $end
   $var wire 32 4 readData_M [31:0] $end
   $var wire  1 1 s $end
   $var wire  1 - sb $end
   $var wire  1 , sh $end
   $var wire  1 + sw $end
   $var wire 32 3 writeData_M [31:0] $end
   $scope module hbw $end
    $var wire 32 ; BYTE_LEN [31:0] $end
    $var wire 32 9 CPU_WORD [31:0] $end
    $var wire 32 : HALF_LEN [31:0] $end
    $var wire  8 ' b [7:0] $end
    $var wire 32 % be [31:0] $end
    $var wire 32 # data [31:0] $end
    $var wire 32 4 dout [31:0] $end
    $var wire 16 & h [15:0] $end
    $var wire 32 $ he [31:0] $end
    $var wire  1 0 lb $end
    $var wire  1 / lh $end
    $var wire  1 . lw $end
    $var wire  1 1 s $end
    $scope module h_e $end
     $var wire 32 : HALF_LEN [31:0] $end
     $var wire 32 9 WORD_LENGTH [31:0] $end
     $var wire 16 & din [15:0] $end
     $var wire 32 $ dout [31:0] $end
     $var wire  1 1 s $end
     $var wire  1 ( sign $end
    $upscope $end
    $scope module s_e $end
     $var wire 32 ; BYTE_LEN [31:0] $end
     $var wire 32 9 WORD_LENGTH [31:0] $end
     $var wire  8 ' din [7:0] $end
     $var wire 32 % dout [31:0] $end
     $var wire  1 1 s $end
     $var wire  1 ) sign $end
    $upscope $end
   $upscope $end
   $scope module ram $end
    $var wire 32 9 ADDRESS_LENGTH [31:0] $end
    $var wire 32 ; WORD_LENGTH [31:0] $end
    $var wire 32 2 a [31:0] $end
    $var wire  1 * clk $end
    $var wire  8 5 d0 [7:0] $end
    $var wire  8 6 d1 [7:0] $end
    $var wire  8 7 d2 [7:0] $end
    $var wire  8 8 d3 [7:0] $end
    $var wire 32 # rd [31:0] $end
    $var wire  1 - sb $end
    $var wire  1 , sh $end
    $var wire  1 + sw $end
    $var wire 32 3 wd [31:0] $end
   $upscope $end
  $upscope $end
 $upscope $end
$enddefinitions $end


#0
b00000000000000000000000000000000 #
b00000000000000000000000000000000 $
b00000000000000000000000000000000 %
b0000000000000000 &
b00000000 '
0(
0)
1*
0+
0,
0-
0.
0/
00
01
b00000000000000000000000000000000 2
b00000000000000000000000000000000 3
b00000000000000000000000000000000 4
b00000000 5
b00000000 6
b00000000 7
b00000000 8
b00000000000000000000000000100000 9
b00000000000000000000000000010000 :
b00000000000000000000000000001000 ;
#1
0*
#2
1*
1+
b00000000000000000001000000000001 2
b11111111111111111111111111111111 3
b11111111 5
b11111111 6
b11111111 7
b11111111 8
#3
0*
#4
b11111111111111111111111111111111 #
b00000000000000001111111111111111 $
b00000000000000000000000011111111 %
b1111111111111111 &
b11111111 '
1*
#5
0*
#6
1*
#7
0*
#8
1*
0+
1,
1/
11
b00000000000000001000100010001000 3
b10001000 5
b10001000 6
b00000000 7
b00000000 8
#9
b11111111111111111111111111111111 $
b11111111111111111111111111111111 %
1(
1)
0*
b11111111111111111111111111111111 4
#10
b11111111111111111000100010001000 #
b11111111111111111000100010001000 $
b11111111111111111111111110001000 %
b1000100010001000 &
b10001000 '
1*
b11111111111111111000100010001000 4
#11
0*
#12
1*
0,
1-
0/
b00000000000000000000000010000001 3
b10000001 5
b00000000 6
#13
0*
b00000000000000000000000000000000 4
#14
b11111111111111111000100010000001 #
b11111111111111111000100010000001 $
b11111111111111111111111110000001 %
b1000100010000001 &
b10000001 '
1*
#15
0*
#16
1*
0-
10
#17
0*
b11111111111111111111111110000001 4
